climopy/__init__.py
climopy/const.py
climopy/diff.py
climopy/downloads.py
climopy/spectral.py
climopy/spherical.py
climopy/units.py
climopy/utils.py
climopy/var.py
climopy/waves.py
climopy/externals/__init__.py
climopy/internals/__init__.py
climopy/internals/array.py
climopy/internals/docstring.py
climopy/internals/quack.py
climopy/internals/warnings.py
climopy-0.1.0.dist-info/LICENSE.txt
climopy-0.1.0.dist-info/METADATA
climopy-0.1.0.dist-info/WHEEL
climopy-0.1.0.dist-info/top_level.txt
climopy-0.1.0.dist-info/RECORD
