Metadata-Version: 2.1
Name: climopy
Version: 0.1.0
Summary: A data analysis toolkit for climate scientists.
Home-page: https://climopy.readthedocs.io
Author: Luke Davis
Author-email: lukelbd@gmail.com
Maintainer: Luke Davis
Maintainer-email: lukelbd@gmail.com
License: MIT
Project-URL: Bug Tracker, https://github.com/lukelbd/climopy/issues
Project-URL: Documentation, https://climopy.readthedocs.io
Project-URL: Source Code, https://github.com/lukelbd/climopy
Platform: UNKNOWN
Classifier: License :: OSI Approved :: MIT License
Classifier: Operating System :: OS Independent
Classifier: Intended Audience :: Science/Research
Classifier: Programming Language :: Python :: 3 :: Only
Classifier: Programming Language :: Python :: 3.8
Requires-Python: >=3.8.0
Requires-Dist: numpy
Requires-Dist: scipy
Requires-Dist: pint
Requires-Dist: pandas
Requires-Dist: xarray
